Changelog.txt
LICENSE.txt
MANIFEST.in
README.txt
TODO.txt
__main__.py
sample.ini
setup.cfg
setup.py
tcpr
TcpProxyReflector.egg-info/PKG-INFO
TcpProxyReflector.egg-info/SOURCES.txt
TcpProxyReflector.egg-info/dependency_links.txt
TcpProxyReflector.egg-info/top_level.txt
contrib/SRPSocket.tgz
tcprlib/__init__.py
tcprlib/apps.py
tcprlib/tcpr.py
tcprlib/srplib/README.txt
tcprlib/srplib/__init__.py
tcprlib/srplib/asyn.py
tcprlib/srplib/sock.py
tcprlib/srplib/srplib.py