Metadata-Version: 1.0
Name: TcpProxyReflector
Version: 0.1.3
Summary: Set of libraries and programs to access internal network resources from outside the LAN via a remote server, without any port forwarding
Home-page: http://blog.magiksys.net/software/tcp-proxy-reflector
Author: Alain Spineux
Author-email: alain.spineux@gmail.com
License: GPL
Platform: UNKNOWN
Classifier: Development Status :: 4 - Beta
Classifier: Intended Audience :: Developers
Classifier: License :: OSI Approved :: GNU General Public License (GPL)
Classifier: Operating System :: OS Independent
Classifier: Topic :: System :: Networking
Classifier: Topic :: Internet
